{
  "projectId": "650750d21e4a6a589be3",
  "projectName": "LangX",
  "functions": [
    {
      "$id": "push-notification-with-fcm",
      "name": "push-notification-with-fcm",
      "runtime": "node-18.0",
      "execute": [],
      "events": [
        "databases.650750f16cd0c482bb83.collections.65075108a4025a4f5bd7.documents.*.create"
      ],
      "schedule": "",
      "timeout": 15,
      "enabled": true,
      "logging": true,
      "entrypoint": "src/main.js",
      "commands": "npm install",
      "ignore": ["node_modules", ".npm"],
      "path": "functions/push-notification-with-fcm"
    },
    {
      "$id": "total-unseen",
      "name": "total-unseen",
      "runtime": "node-18.0",
      "execute": [],
      "events": [
        "databases.650750f16cd0c482bb83.collections.65075108a4025a4f5bd7.documents.*.create",
        "databases.650750f16cd0c482bb83.collections.65075108a4025a4f5bd7.documents.*.update"
      ],
      "schedule": "",
      "timeout": 15,
      "enabled": true,
      "logging": true,
      "entrypoint": "src/main.js",
      "commands": "npm install",
      "ignore": ["node_modules", ".npm"],
      "path": "functions/total-unseen"
    },
    {
      "$id": "total-unseen-v2",
      "name": "total-unseen-v2",
      "runtime": "node-18.0",
      "execute": [],
      "events": [
        "databases.650750f16cd0c482bb83.collections.6507510fc71f989d5d1c.documents.*.update"
      ],
      "schedule": "",
      "timeout": 15,
      "enabled": true,
      "logging": true,
      "entrypoint": "src/main.js",
      "commands": "npm install",
      "ignore": ["node_modules", ".npm"],
      "path": "functions/total-unseen-v2"
    },
    {
      "$id": "visit-notifications",
      "name": "visit-notifications",
      "runtime": "node-18.0",
      "execute": [],
      "events": [],
      "schedule": "",
      "timeout": 15,
      "enabled": true,
      "logging": true,
      "entrypoint": "src/main.js",
      "commands": "npm install",
      "ignore": ["node_modules", ".npm"],
      "path": "functions/visit-notifications"
    },
    {
      "$id": "day-streaks",
      "name": "day-streaks",
      "runtime": "node-18.0",
      "execute": [],
      "events": [],
      "schedule": "",
      "timeout": 15,
      "enabled": true,
      "logging": true,
      "entrypoint": "src/main.js",
      "commands": "npm install",
      "ignore": ["node_modules", ".npm"],
      "path": "functions/day-streaks"
    },
    {
      "$id": "token-distribution",
      "name": "token-distribution",
      "runtime": "node-18.0",
      "execute": [],
      "events": [
        "databases.650750f16cd0c482bb83.collections.65103e2d3a6b4d9494c8.documents.*.update",
        "databases.650750f16cd0c482bb83.collections.65075108a4025a4f5bd7.documents.*.create"
      ],
      "schedule": "",
      "timeout": 15,
      "enabled": true,
      "logging": true,
      "entrypoint": "src/main.js",
      "commands": "npm install",
      "ignore": ["node_modules", ".npm"],
      "path": "functions/token-distribution"
    },
    {
      "$id": "token-checkout",
      "name": "token-checkout",
      "runtime": "node-18.0",
      "execute": [],
      "events": [],
      "schedule": "0 0 * * *",
      "timeout": 59,
      "enabled": true,
      "logging": true,
      "entrypoint": "src/main.js",
      "commands": "npm install",
      "ignore": ["node_modules", ".npm"],
      "path": "functions/token-checkout"
    },
    {
      "$id": "discord-sync",
      "name": "discord-sync",
      "runtime": "node-18.0",
      "execute": ["users"],
      "events": [],
      "schedule": "",
      "timeout": 15,
      "enabled": true,
      "logging": true,
      "entrypoint": "src/main.js",
      "commands": "npm install",
      "ignore": ["node_modules", ".npm"],
      "path": "functions/discord-sync"
    }
  ]
}
